duyan_download_task/__init__.py
duyan_download_task/constants.py
duyan_download_task/model.py
duyan_download_task/scheduler.py
duyan_download_task/task.py
duyan_download_task/test/__init__.py
duyan_download_task/test/scheduler_test.py
duyan_download_task/test/task_test.py
duyan_download_task/utils/__init__.py
duyan_download_task/utils/common_utils.py
duyan_download_task/utils/config_util.py
duyan_download_task/utils/logger_util.py
duyan_download_task/utils/mysql_util.py
duyan_download_task-0.0.10.dist-info/LICENSE
duyan_download_task-0.0.10.dist-info/METADATA
duyan_download_task-0.0.10.dist-info/WHEEL
duyan_download_task-0.0.10.dist-info/top_level.txt
duyan_download_task-0.0.10.dist-info/RECORD
