Metadata-Version: 2.1
Name: duyan-download-task
Version: 0.0.10
Summary: Using for Debug, finding problem
Home-page: https://github.com/pypa/sampleproject
Author: WuMenghao
Author-email: menghao.wu@duyansoft.com
License: UNKNOWN
Project-URL: Bug Tracker, https://github.com/pypa/sampleproject/issues
Platform: UNKNOWN
Classifier: Programming Language :: Python :: 3
Classifier: License :: OSI Approved :: MIT License
Classifier: Operating System :: OS Independent
Requires-Python: >=3.6
License-File: LICENSE
Requires-Dist: APScheduler
Requires-Dist: loguru
Requires-Dist: PyMySQL
Requires-Dist: redis
Requires-Dist: DBUtils (==1.3)
